setup.cfg
setup.py
LerpnApp/__init__.py
LerpnApp/__main__.py
LerpnApp/commands.py
LerpnApp/curses_stuff.py
LerpnApp/env.py
LerpnApp/extramath.py
LerpnApp/nums.py
LerpnApp/tui.py
lerpn.egg-info/PKG-INFO
lerpn.egg-info/SOURCES.txt
lerpn.egg-info/dependency_links.txt
lerpn.egg-info/entry_points.txt
lerpn.egg-info/top_level.txt