Metadata-Version: 1.1
Name: lerpn
Version: 2.0
Summary: Linux? Engineering RPN calculator
Home-page: https://github.com/cpavlina/lerpn
Author: Chris Pavlina
Author-email: pavlina.chris@gmail.com
License: UNKNOWN
Download-URL: https://github.com/cpavlina/lerpn/tarball/2.0
Keywords: calculator,rpn
Platform: UNKNOWN
Classifier: Development Status :: 5 - Production/Stable
Classifier: Environment :: Console :: Curses
Classifier: Topic :: Utilities
Classifier: License :: Public Domain
